{
  "不够": "không đủ; chưa đủ",
  "作品": "tác phẩm",
  "倍": "lần; gấp (bội số)",
  "免费": "miễn phí",
  "准": "cho phép; chuẩn; chính xác",
  "动作": "động tác; hành động",
  "反对": "phản đối; chống lại",
  "否则": "nếu không thì; bằng không",
  "嗯": "ừ; ờ (từ đệm)",
  "型": "kiểu; loại; mẫu",
  "女性": "nữ giới; phái nữ",
  "左右": "trái phải; khoảng chừng",
  "按照": "theo; căn cứ vào",
  "效果": "hiệu quả; kết quả",
  "普通": "phổ thông; bình thường",
  "有效": "hiệu quả; có hiệu lực",
  "牌": "quân bài; biển hiệu; nhãn hiệu",
  "空": "trống; rỗng; bầu trời",
  "经济": "kinh tế",
  "要是": "nếu; nếu như",
  "讨厌": "ghét; chán ghét; đáng ghét",
  "输": "thua; thất bại; vận chuyển",
  "醒": "tỉnh; thức dậy",
  "重点": "trọng điểm; điểm chính",
  "竟然": "không ngờ; lại (bất ngờ)"
}
